pytro.py
pytro-0.1.2.dist-info/METADATA
pytro-0.1.2.dist-info/WHEEL
pytro-0.1.2.dist-info/dependency_links.txt
pytro-0.1.2.dist-info/top_level.txt
pytro-0.1.2.dist-info/RECORD
